riscv_defines_g7.v
// riscv_defines_g7.v
`define R_TYPE      7'b0110011
`define I_TYPE_LOAD 7'b0000011
`define S_TYPE      7'b0100011
`define B_TYPE      7'b1100011

`define ALU_ADD     4'b0000
`define ALU_SUB     4'b0001
`define ALU_AND     4'b0010
`define ALU_OR      4'b0011
`define ALU_SRL     4'b0101

data_memory_byte.v
// data_memory_byte.v
module data_memory_byte (
    input  wire        clk,       input  wire        MemWrite,
    input  wire        MemRead,   input  wire [31:0] address,
    input  wire [31:0] write_data,output wire [31:0] read_data
);
    reg [7:0] mem [4095:0];
    assign read_data = MemRead ? {{24{mem[address][7]}}, mem[address]} : 32'bz;
    always @(posedge clk) begin
        if (MemWrite) mem[address] <= write_data[7:0];
    end
endmodule

alu_g7.v
// alu_g7.v
`include "riscv_defines_g7.v"
module alu_g7 (
    input  wire [31:0] a,
    input  wire [31:0] b,
    input  wire [3:0]  ALUControl,
    output reg  [31:0] result,
    output wire        zero
);
    always @(*) begin
        case (ALUControl)
            `ALU_ADD: result = a + b;
            `ALU_SUB: result = a - b;
            `ALU_AND: result = a & b;
            `ALU_OR:  result = a | b;
            `ALU_SRL: result = a >> b[4:0];
            default:  result = 32'hxxxxxxxx;
        endcase
    end
    assign zero = (result == 32'b0);
endmodule

alu_control_g7.v
// alu_control_g7.v
`include "riscv_defines_g7.v"
module alu_control_g7 (
    input  wire [1:0] ALUOp,    input wire [6:0] funct7,
    input  wire [2:0] funct3,   output reg [3:0] ALUControl
);
    always @(*) begin
        case (ALUOp)
            2'b00: ALUControl = `ALU_ADD;
            2'b01: ALUControl = `ALU_SUB;
            2'b10: case (funct3)
                    3'b000: ALUControl = `ALU_ADD;
                    3'b110: ALUControl = `ALU_OR;
                    3'b111: ALUControl = `ALU_AND;
                    3'b101: ALUControl = `ALU_SRL;
                    default: ALUControl = 4'bxxxx;
                   endcase
            default: ALUControl = 4'bxxxx;
        endcase
    end
endmodule

reg_file.v
// reg_file.v
module reg_file (
    input  wire        clk,
    input  wire        RegWrite,
    input  wire [4:0]  rs1_addr,
    input  wire [4:0]  rs2_addr,
    input  wire [4:0]  rd_addr,
    input  wire [31:0] rd_data,
    output wire [31:0] rs1_data,
    output wire [31:0] rs2_data
);
    reg [31:0] registers [31:0];
    always @(posedge clk) begin
        if (RegWrite && (rd_addr != 5'b0)) begin
            registers[rd_addr] <= rd_data;
        end
    end
    assign rs1_data = (rs1_addr == 5'b0) ? 32'b0 : registers[rs1_addr];
    assign rs2_data = (rs2_addr == 5'b0) ? 32'b0 : registers[rs2_addr];
endmodule

control_g7.v
// control_g7.v
`include "riscv_defines_g7.v"
module control_g7 (
    input  wire [6:0] opcode,
    output reg        RegWrite, output reg ALUSrc,   output reg MemtoReg,
    output reg        MemRead,  output reg MemWrite, output reg Branch,
    output reg [1:0]  ALUOp
);
    always @(*) begin
        RegWrite=0; ALUSrc=0; MemtoReg=0; MemRead=0; MemWrite=0; Branch=0; ALUOp=2'b00;
        case (opcode)
            `R_TYPE:      begin RegWrite = 1'b1; ALUOp = 2'b10; end
            `I_TYPE_LOAD: begin RegWrite = 1'b1; ALUSrc = 1'b1; MemtoReg = 1'b1; MemRead = 1'b1; ALUOp = 2'b00; end
            `S_TYPE:      begin ALUSrc = 1'b1; MemWrite = 1'b1; ALUOp = 2'b00; end
            `B_TYPE:      begin Branch = 1'b1; ALUOp = 2'b01; end
        endcase
    end
endmodule

instruction_memory.v
// instruction_memory.v
module instruction_memory (
    input  wire [31:0] address,
    output wire [31:0] instruction
);
    reg [31:0] mem [1023:0];
    initial $readmemh("meu_programa_g7.hex", mem);
    assign instruction = mem[address[31:2]];
endmodule

pc.v
// pc.v
module pc (
    input  wire        clk,
    input  wire        rst,
    input  wire [31:0] pc_next,
    output reg  [31:0] pc_current
);
    always @(posedge clk or posedge rst) begin
        if (rst) pc_current <= 32'b0;
        else     pc_current <= pc_next;
    end
endmodule

riscv_processor_g7.v
// riscv_processor_g7.v
`include "riscv_defines_g7.v"
module riscv_processor_g7 (input wire clk, input wire rst);
    wire [31:0] pc_current, pc_next, pc_plus_4;
    wire [31:0] instruction;
    wire [6:0]  opcode;
    wire [4:0]  rd_addr, rs1_addr, rs2_addr;
    wire [2:0]  funct3;
    wire [6:0]  funct7;
    reg [31:0] immediate_extended;
    wire        RegWrite, ALUSrc, MemtoReg, MemRead, MemWrite, Branch;
    wire [1:0]  ALUOp;
    wire [3:0]  ALUControl;
    wire        PCSrc;
    wire [31:0] rs1_data, rs2_data, write_back_data;
    wire [31:0] alu_input_b, alu_result;
    wire        alu_zero;
    wire [31:0] mem_read_data;
    wire [31:0] branch_target_addr;

    assign PCSrc = Branch & alu_zero;
    assign pc_next = PCSrc ? branch_target_addr : pc_plus_4;
    pc pc_reg (.clk(clk), .rst(rst), .pc_next(pc_next), .pc_current(pc_current));
    assign pc_plus_4 = pc_current + 32'd4;
    instruction_memory imem (.address(pc_current), .instruction(instruction));

    assign opcode   = instruction[6:0];   assign rd_addr  = instruction[11:7];
    assign funct3   = instruction[14:12];  assign rs1_addr = instruction[19:15];
    assign rs2_addr = instruction[24:20];  assign funct7   = instruction[31:25];

    control_g7 main_control (.opcode(opcode), .RegWrite(RegWrite), .ALUSrc(ALUSrc), .MemtoReg(MemtoReg), .MemRead(MemRead), .MemWrite(MemWrite), .Branch(Branch), .ALUOp(ALUOp));
    reg_file reg_file_unit (.clk(clk), .RegWrite(RegWrite), .rs1_addr(rs1_addr), .rs2_addr(rs2_addr), .rd_addr(rd_addr), .rd_data(write_back_data), .rs1_data(rs1_data), .rs2_data(rs2_data));

    always @(*) begin
        case (opcode)
            `I_TYPE_LOAD: immediate_extended = {{20{instruction[31]}}, instruction[31:20]};
            `S_TYPE:      immediate_extended = {{20{instruction[31]}}, instruction[31:25], instruction[11:7]};
            `B_TYPE:      immediate_extended = {{20{instruction[31]}}, instruction[7], instruction[30:25], instruction[11:8], 1'b0};
            default:      immediate_extended = 32'hxxxxxxxx;
        endcase
    end

    alu_control_g7 alu_control_unit (.ALUOp(ALUOp), .funct7(funct7), .funct3(funct3), .ALUControl(ALUControl));
    assign alu_input_b = ALUSrc ? immediate_extended : rs2_data;
    alu_g7 alu_unit (.a(rs1_data), .b(alu_input_b), .ALUControl(ALUControl), .result(alu_result), .zero(alu_zero));
    assign branch_target_addr = pc_current + immediate_extended;
    data_memory_byte data_mem_unit (.clk(clk), .MemWrite(MemWrite), .MemRead(MemRead), .address(alu_result), .write_data(rs2_data), .read_data(mem_read_data));
    assign write_back_data = MemtoReg ? mem_read_data : alu_result;
endmodule

testbench_g7.v
// testbench_g7.v
`timescale 1ns/1ps
module testbench_g7;
    reg clk;
    reg rst;
    riscv_processor_g7 dut (.clk(clk), .rst(rst));
    initial begin
        clk = 0;
        forever #5 clk = ~clk;
    end
    initial begin
        $dumpfile("waveform.vcd");
        $dumpvars(0, dut);
        rst = 1; #20; rst = 0;
        #200;
        $display("Simulacao finalizada.");
        $finish;
    end
endmodule

waveform.vcd
$date
	Tue Aug 12 20:30:59 2025
$end
$version
	Icarus Verilog
$end
$timescale
	1ps
$end
$scope module testbench_g7 $end
$scope module dut $end
$var wire 1 ! PCSrc $end
$var wire 1 " clk $end
$var wire 1 # rst $end
$var wire 32 $ write_back_data [31:0] $end
$var wire 32 % rs2_data [31:0] $end
$var wire 5 & rs2_addr [4:0] $end
$var wire 32 ' rs1_data [31:0] $end
$var wire 5 ( rs1_addr [4:0] $end
$var wire 5 ) rd_addr [4:0] $end
$var wire 32 * pc_plus_4 [31:0] $end
$var wire 32 + pc_next [31:0] $end
$var wire 32 , pc_current [31:0] $end
$var wire 7 - opcode [6:0] $end
$var wire 32 . mem_read_data [31:0] $end
$var wire 32 / instruction [31:0] $end
$var wire 7 0 funct7 [6:0] $end
$var wire 3 1 funct3 [2:0] $end
$var wire 32 2 branch_target_addr [31:0] $end
$var wire 1 3 alu_zero $end
$var wire 32 4 alu_result [31:0] $end
$var wire 32 5 alu_input_b [31:0] $end
$var wire 1 6 RegWrite $end
$var wire 1 7 MemtoReg $end
$var wire 1 8 MemWrite $end
$var wire 1 9 MemRead $end
$var wire 1 : Branch $end
$var wire 1 ; ALUSrc $end
$var wire 2 < ALUOp [1:0] $end
$var wire 4 = ALUControl [3:0] $end
$var reg 32 > immediate_extended [31:0] $end
$scope module alu_control_unit $end
$var wire 3 ? funct3 [2:0] $end
$var wire 7 @ funct7 [6:0] $end
$var wire 2 A ALUOp [1:0] $end
$var reg 4 B ALUControl [3:0] $end
$upscope $end
$scope module alu_unit $end
$var wire 4 C ALUControl [3:0] $end
$var wire 32 D b [31:0] $end
$var wire 1 3 zero $end
$var wire 32 E a [31:0] $end
$var reg 32 F result [31:0] $end
$upscope $end
$scope module data_mem_unit $end
$var wire 32 G address [31:0] $end
$var wire 1 " clk $end
$var wire 32 H write_data [31:0] $end
$var wire 32 I read_data [31:0] $end
$var wire 1 8 MemWrite $end
$var wire 1 9 MemRead $end
$upscope $end
$scope module imem $end
$var wire 32 J instruction [31:0] $end
$var wire 32 K address [31:0] $end
$upscope $end
$scope module main_control $end
$var wire 7 L opcode [6:0] $end
$var reg 2 M ALUOp [1:0] $end
$var reg 1 ; ALUSrc $end
$var reg 1 : Branch $end
$var reg 1 9 MemRead $end
$var reg 1 8 MemWrite $end
$var reg 1 7 MemtoReg $end
$var reg 1 6 RegWrite $end
$upscope $end
$scope module pc_reg $end
$var wire 1 " clk $end
$var wire 32 N pc_next [31:0] $end
$var wire 1 # rst $end
$var reg 32 O pc_current [31:0] $end
$upscope $end
$scope module reg_file_unit $end
$var wire 1 6 RegWrite $end
$var wire 1 " clk $end
$var wire 5 P rd_addr [4:0] $end
$var wire 32 Q rd_data [31:0] $end
$var wire 5 R rs1_addr [4:0] $end
$var wire 5 S rs2_addr [4:0] $end
$var wire 32 T rs2_data [31:0] $end
$var wire 32 U rs1_data [31:0] $end
$upscope $end
$upscope $end
$upscope $end
$enddefinitions $end
#0
$dumpvars
b0 U
bx T
b101 S
b0 R
bx Q
b1 P
b0 O
b100 N
b0 M
b10011 L
b0 K
b10100000000000010010011 J
bz I
bx H
bx G
bx F
b0 E
bx D
b0 C
b0 B
b0 A
b0 @
b0 ?
bx >
b0 =
b0 <
0;
0:
09
08
07
06
bx 5
bx 4
x3
bx 2
b0 1
b0 0
b10100000000000010010011 /
bz .
b10011 -
b0 ,
b100 +
b100 *
b1 )
b0 (
b0 '
b101 &
bx %
bx $
1#
0"
0!
$end
#5000
1"
#10000
0"
#15000
1"
#20000
0"
0#
#25000
b1010 &
b1010 S
b10 )
b10 P
b101000000000000100010011 /
b101000000000000100010011 J
b1000 +
b1000 N
b1000 *
b100 ,
b100 K
b100 O
1"
#30000
0"
#35000
bx '
bx E
bx U
b10 <
b10 A
b10 M
16
b10 &
b10 S
b1 (
b1 R
b11 )
b11 P
b110011 -
b110011 L
b1000001000000110110011 /
b1000001000000110110011 J
b1100 +
b1100 N
b1100 *
b1000 ,
b1000 K
b1000 O
1"
#40000
0"
#45000
b100 $
b100 Q
03
b100 4
b100 F
b100 G
b100 5
b100 D
b0 '
b0 E
b0 U
18
1;
b0 <
b0 A
b0 M
06
b10000 2
b100 >
b11 &
b11 S
b0 (
b0 R
b100 )
b100 P
b100011 -
b100011 L
b1100000000001000100011 /
b1100000000001000100011 J
b10000 +
b10000 N
b10000 *
b1100 ,
b1100 K
b1100 O
1"
#50000
0"
#55000
bx $
bx Q
x3
bx 4
bx F
bx G
bx '
bx E
bx U
08
0;
bx 5
bx D
bx 0
bx @
bx &
bx S
bx (
bx R
bx 1
bx ?
bx )
bx P
bx -
bx L
bx >
bx /
bx J
b10100 +
b10100 N
bx 2
b10100 *
b10000 ,
b10000 K
b10000 O
1"
#60000
0"
#65000
b11000 +
b11000 N
b11000 *
b10100 ,
b10100 K
b10100 O
1"
#70000
0"
#75000
b11100 +
b11100 N
b11100 *
b11000 ,
b11000 K
b11000 O
1"
#80000
0"
#85000
b100000 +
b100000 N
b100000 *
b11100 ,
b11100 K
b11100 O
1"
#90000
0"
#95000
b100100 +
b100100 N
b100100 *
b100000 ,
b100000 K
b100000 O
1"
#100000
0"
#105000
b101000 +
b101000 N
b101000 *
b100100 ,
b100100 K
b100100 O
1"
#110000
0"
#115000
b101100 +
b101100 N
b101100 *
b101000 ,
b101000 K
b101000 O
1"
#120000
0"
#125000
b110000 +
b110000 N
b110000 *
b101100 ,
b101100 K
b101100 O
1"
#130000
0"
#135000
b110100 +
b110100 N
b110100 *
b110000 ,
b110000 K
b110000 O
1"
#140000
0"
#145000
b111000 +
b111000 N
b111000 *
b110100 ,
b110100 K
b110100 O
1"
#150000
0"
#155000
b111100 +
b111100 N
b111100 *
b111000 ,
b111000 K
b111000 O
1"
#160000
0"
#165000
b1000000 +
b1000000 N
b1000000 *
b111100 ,
b111100 K
b111100 O
1"
#170000
0"
#175000
b1000100 +
b1000100 N
b1000100 *
b1000000 ,
b1000000 K
b1000000 O
1"
#180000
0"
#185000
b1001000 +
b1001000 N
b1001000 *
b1000100 ,
b1000100 K
b1000100 O
1"
#190000
0"
#195000
b1001100 +
b1001100 N
b1001100 *
b1001000 ,
b1001000 K
b1001000 O
1"
#200000
0"
#205000
b1010000 +
b1010000 N
b1010000 *
b1001100 ,
b1001100 K
b1001100 O
1"
#210000
0"
#215000
b1010100 +
b1010100 N
b1010100 *
b1010000 ,
b1010000 K
b1010000 O
1"
